pos2key/__init__.py
pos2key/config.py
pos2key-0.0.2.dist-info/licenses/LICENSE
pos2key-0.0.2.dist-info/METADATA
pos2key-0.0.2.dist-info/WHEEL
pos2key-0.0.2.dist-info/top_level.txt
pos2key-0.0.2.dist-info/RECORD
