Metadata-Version: 2.4
Name: pos2key
Version: 0.0.2
Summary: A small example package
License-Expression: GPL-3.0
Project-URL: Homepage, https://github.com/mysticshirou/pos2key
Classifier: Programming Language :: Python :: 3
Classifier: Operating System :: OS Independent
Requires-Python: >=3.9
License-File: LICENSE
Requires-Dist: build>=1.3.0
Requires-Dist: requests
Dynamic: license-file
